1_design/resource_shared_datapath.v
`timescale 1ns / 1ps

module resource_shared_datapath #(
    parameter DATA_WIDTH = 8,
    // (A+B) or (C-D) can be 9 bits (8 bits + carry/sign)
    parameter TEMP_WIDTH = 9,
    // (9-bit * 9-bit) = 18 bits
    parameter Z_WIDTH = 18
) (
    input wire clk,
    input wire rst_n, // Active-low async reset
    input wire start, // Start computation
    
    // Data Inputs
    input wire [DATA_WIDTH-1:0] A,
    input wire [DATA_WIDTH-1:0] B,
    input wire [DATA_WIDTH-1:0] C,
    input wire [DATA_WIDTH-1:0] D,
    
    // Data Output
    output wire [Z_WIDTH-1:0] Z,
    output wire done
);

    // --- FSM State Definitions ---
    parameter [2:0] 
        S_IDLE     = 3'b000,
        S_CALC_ADD = 3'b001,
        S_CALC_SUB = 3'b010,
        S_CALC_MULT = 3'b011,
        S_DONE     = 3'b100;

    // --- FSM State Registers ---
    reg [2:0] state, next_state;

    // --- Datapath Registers ---
    reg [DATA_WIDTH-1:0] a_reg, b_reg, c_reg, d_reg;
    reg [TEMP_WIDTH-1:0] temp1_reg; // Holds (A+B)
    reg [TEMP_WIDTH-1:0] temp2_reg; // Holds (C-D)
    reg [Z_WIDTH-1:0] z_reg;     // Holds final result

    // --- Datapath Wires ---
    wire [DATA_WIDTH-1:0] alu_in1;
    wire [DATA_WIDTH-1:0] alu_in2;
    wire alu_sub;
    wire [TEMP_WIDTH-1:0] alu_out;
    wire [Z_WIDTH-1:0] mul_out;

    // --- FSM State Transition Logic (Sequential) ---
    always @(posedge clk or negedge rst_n) begin
        if (!rst_n) begin
            state <= S_IDLE;
        end else begin
            state <= next_state;
        end
    end

    // --- Datapath Register Loading (Sequential) ---
    always @(posedge clk or negedge rst_n) begin
        if (!rst_n) begin
            // Reset all datapath registers
            a_reg <= 0;
            b_reg <= 0;
            c_reg <= 0;
            d_reg <= 0;
            temp1_reg <= 0;
            temp2_reg <= 0;
            z_reg <= 0;
        end else begin
            // FSM-controlled loading
            if (state == S_IDLE && start) begin
                a_reg <= A;
                b_reg <= B;
                c_reg <= C;
                d_reg <= D;
            end
            
            if (state == S_CALC_ADD) begin
                temp1_reg <= alu_out;
            end
            
            if (state == S_CALC_SUB) begin
                temp2_reg <= alu_out;
            end
            
            if (state == S_CALC_MULT) begin
                z_reg <= mul_out;
            end
        end
    end

    // --- FSM Next-State Logic (Combinational) ---
    always @(*) begin
        case (state)
            S_IDLE:     next_state = start ? S_CALC_ADD : S_IDLE;
            S_CALC_ADD: next_state = S_CALC_SUB;
            S_CALC_SUB: next_state = S_CALC_MULT;
            S_CALC_MULT:next_state = S_DONE;
            S_DONE:     next_state = S_IDLE;
            default:    next_state = S_IDLE;
        endcase
    end

    // --- Datapath Logic (Combinational) ---
    
    // Muxes for ALU inputs
    assign alu_in1 = (state == S_CALC_ADD) ? a_reg : c_reg;
    assign alu_in2 = (state == S_CALC_ADD) ? b_reg : d_reg;
    
    // Control signal for ALU
    assign alu_sub = (state == S_CALC_SUB); // 1 for SUB, 0 for ADD

    // Resource-Shared ALU (Adder/Subtractor)
    // We use 9 bits to handle signed results and carry-outs
    assign alu_out = (alu_sub) ? 
                   ($signed(alu_in1) - $signed(alu_in2)) : 
                   ($signed(alu_in1) + $signed(alu_in2));

    // Multiplier
    // Multiplies the 9-bit signed temporary results
    assign mul_out = $signed(temp1_reg) * $signed(temp2_reg);

    // --- Output Assignments ---
    assign Z = z_reg;
    assign done = (state == S_DONE);

endmodule

2_work/datapath_tb.v
`timescale 1ns / 1ps

module datapath_tb;

    // Parameters
    localparam DATA_WIDTH = 8;
    localparam Z_WIDTH = 18;
    localparam CLK_PERIOD = 10;

    // Signals
    reg clk;
    reg rst_n;
    reg start;
    reg [DATA_WIDTH-1:0] A, B, C, D;
    wire [Z_WIDTH-1:0] Z;
    wire done;
    
    integer errors = 0;

    // Instantiate DUT
    resource_shared_datapath #(
        .DATA_WIDTH(DATA_WIDTH),
        .Z_WIDTH(Z_WIDTH)
    ) dut (
        .clk(clk),
        .rst_n(rst_n),
        .start(start),
        .A(A), .B(B), .C(C), .D(D),
        .Z(Z),
        .done(done)
    );

    // Clock Generator
    initial begin
        clk = 0;
        forever #(CLK_PERIOD / 2) clk = ~clk;
    end

    // Test Sequence
    initial begin
        $dumpfile("wave.vcd");
        $dumpvars(0, dut);

        // 1. Reset
        rst_n = 0;
        start = 0;
        A = 0; B = 0; C = 0; D = 0;
        #(CLK_PERIOD * 2);
        rst_n = 1;
        @(posedge clk);
        $display("--- System Reset Complete ---");

	// Test 1: Simple positive
        // (5 + 10) * (8 - 3) = 15 * 5 = 75
        apply_and_check(8'd5, 8'd10, 8'd8, 8'd3, 18'd75);
        
        // Test 2: Negative result
        // (10 + 2) * (5 - 10) = 12 * -5 = -60
        apply_and_check(8'd10, 8'd2, 8'd5, 8'd10, -18'd60);
        
        // Test 3: Corrected Expected Value (was -256)
        // ($signed(8'hFF) + $signed(8'h01)) * ($signed(8'h00) - $signed(8'h01))
        // (-1 + 1) * (0 - 1) = 0 * -1 = 0
        apply_and_check(8'hFF, 8'h01, 8'h00, 8'h01, 18'd0);
        
        // Test 4: Corrected Expected Value (was -21675)
        // ($signed(8'hAA) + $signed(8'h55)) * ($signed(8'h55) - $signed(8'hAA))
        // (-86 + 85) * (85 - (-86)) = -1 * 171 = -171
        apply_and_check(8'hAA, 8'h55, 8'h55, 8'hAA, -18'd171);

        if (errors == 0)
            $display("\n*** ALL TESTS PASSED ***");
        else
            $display("\n*** %0d TESTS FAILED ***", errors);
            
        $finish;
    end

    // Task to apply values, start, and check result
    task apply_and_check;
        input [DATA_WIDTH-1:0] i_A;
        input [DATA_WIDTH-1:0] i_B;
        input [DATA_WIDTH-1:0] i_C;
        input [DATA_WIDTH-1:0] i_D;
        input [Z_WIDTH-1:0]    exp_Z;
        
        @(posedge clk);
        A = i_A;
        B = i_B;
        C = i_C;
        D = i_D;
        start = 1;
        
        @(posedge clk);
        start = 0;

        @(posedge done); // Wait for the 'done' signal
        
        // Check result on the same cycle as 'done'
        if (Z === exp_Z) begin
            $display("PASS: (A=%d, B=%d, C=%d, D=%d) -> Z=%d", $signed(i_A), $signed(i_B), $signed(i_C), $signed(i_D), $signed(Z));
        end else begin
            $display("FAIL: (A=%d, B=%d, C=%d, D=%d) -> Z=%d, Expected=%d", $signed(i_A), $signed(i_B), $signed(i_C), $signed(i_D), $signed(Z), $signed(exp_Z));
            errors = errors + 1;
        end
        @(posedge clk); // Wait one cycle for FSM to return to IDLE
    endtask

endmodule

2_work/wave.vcd
$date
    Nov  4, 2025  19:16:53
$end
$version
    TOOL:	ncsim(64)	15.20-s086
$end
$timescale
    1 ps
$end

$scope module datapath_tb $end

$scope module dut $end
$var parameter 32 !    DATA_WIDTH  $end
$var parameter 32 "    TEMP_WIDTH  $end
$var parameter 32 #    Z_WIDTH  $end
$var wire      1 $    clk  $end
$var wire      1 %    rst_n  $end
$var wire      1 &    start  $end
$var wire      8 '    A [7:0] $end
$var wire      8 (    B [7:0] $end
$var wire      8 )    C [7:0] $end
$var wire      8 *    D [7:0] $end
$var wire     18 +    Z [17:0] $end
$var wire      1 ,    done  $end
$var parameter  3 -    S_IDLE [2:0] $end
$var parameter  3 .    S_CALC_ADD [2:0] $end
$var parameter  3 /    S_CALC_SUB [2:0] $end
$var parameter  3 0    S_CALC_MULT [2:0] $end
$var parameter  3 1    S_DONE [2:0] $end
$var reg       3 2    state [2:0] $end
$var reg       3 3    next_state [2:0] $end
$var reg       8 4    a_reg [7:0] $end
$var reg       8 5    b_reg [7:0] $end
$var reg       8 6    c_reg [7:0] $end
$var reg       8 7    d_reg [7:0] $end
$var reg       9 8    temp1_reg [8:0] $end
$var reg       9 9    temp2_reg [8:0] $end
$var reg      18 :    z_reg [17:0] $end
$var wire      8 ;    alu_in1 [7:0] $end
$var wire      8 <    alu_in2 [7:0] $end
$var wire      1 =    alu_sub  $end
$var wire      9 >    alu_out [8:0] $end
$var wire     18 ?    mul_out [17:0] $end
$upscope $end

$upscope $end

$enddefinitions $end
$dumpvars
b100 1
b11 0
b10 /
b1 .
b0 -
b10010 #
b1001 "
b1000 !
0$
0%
0&
b0 '
b0 (
b0 )
b0 *
b0 +
0,
b0 2
b0 3
b0 4
b0 5
b0 6
b0 7
b0 8
b0 9
b0 :
b0 ;
b0 <
0=
b0 >
b0 ?
$end
#5000
1$
#10000
0$
#15000
1$
#20000
0$
1%
#25000
1$
#30000
0$
#35000
1&
b11 *
b1000 )
b1010 (
b101 '
1$
b1 3
b101 4
b1010 5
b1000 6
b11 7
b1 2
b10 3
b1010 <
b101 ;
b1111 >
#40000
0$
#45000
0&
1$
b1111 8
b10 2
b11 3
1=
b11 <
b1000 ;
b101 >
#50000
0$
#55000
1$
b101 9
b11 2
b100 3
0=
b1001011 ?
b1011 >
#60000
0$
#65000
1$
b1001011 :
b100 2
b0 3
1,
b1001011 +
#70000
0$
#75000
1$
b0 2
0,
#80000
0$
#85000
1&
b1010 *
b101 )
b10 (
b1010 '
1$
b1 3
b1010 4
b10 5
b101 6
b1010 7
b1 2
b10 3
b10 <
b1010 ;
b1100 >
#90000
0$
#95000
0&
1$
b1100 8
b10 2
b11 3
1=
b1010 <
b101 ;
b111100 ?
b111111011 >
#100000
0$
#105000
1$
b111111011 9
b11 2
b100 3
0=
b111111111111000100 ?
b1111 >
#110000
0$
#115000
1$
b111111111111000100 :
b100 2
b0 3
1,
b111111111111000100 +
#120000
0$
#125000
1$
b0 2
0,
#130000
0$
#135000
1&
b1 *
b0 )
b1 (
b11111111 '
1$
b1 3
b11111111 4
b1 5
b0 6
b1 7
b1 2
b10 3
b1 <
b11111111 ;
b0 >
#140000
0$
#145000
0&
1$
b0 8
b10 2
b11 3
1=
b0 ;
b0 ?
b111111111 >
#150000
0$
#155000
1$
b111111111 9
b11 2
b100 3
0=
b1 >
#160000
0$
#165000
1$
b0 :
b100 2
b0 3
1,
b0 +
#170000
0$
#175000
1$
b0 2
0,
#180000
0$
#185000
1&
b10101010 *
b1010101 )
b1010101 (
b10101010 '
1$
b1 3
b10101010 4
b1010101 5
b1010101 6
b10101010 7
b1 2
b10 3
b1010101 <
b10101010 ;
b111111111 >
#190000
0$
#195000
0&
1$
b111111111 8
b10 2
b11 3
1=
b10101010 <
b1010101 ;
b1 ?
b10101011 >
#200000
0$
#205000
1$
b10101011 9
b11 2
b100 3
0=
b111111111101010101 ?
b111111111 >
#210000
0$
#215000
1$
b111111111101010101 :
b100 2
b0 3
1,
b111111111101010101 +
